torch_ttnn/__init__.py
torch_ttnn/backend.py
torch_ttnn/fx_graphviz.py
torch_ttnn/handle_input_aliasing.py
torch_ttnn/mem_utils.py
torch_ttnn/metrics.py
torch_ttnn/utils.py
torch_ttnn-0.5.4.dist-info/licenses/LICENSE
torch_ttnn-0.5.4.dist-info/METADATA
torch_ttnn-0.5.4.dist-info/WHEEL
torch_ttnn-0.5.4.dist-info/top_level.txt
torch_ttnn-0.5.4.dist-info/RECORD
