Metadata-Version: 2.4
Name: torch-ttnn
Version: 0.5.4
Summary: PyTorch dynamo backend for Tenstorrent TT-NN framework
Home-page: https://github.com/tenstorrent/pytorch2.0_ttnn
Author-email: Tenstorrent <info@tenstorrent.com>
Keywords: torch,ttnn,pytorch2.0,tenstorrent
Classifier: Programming Language :: Python :: 3
Classifier: Operating System :: OS Independent
Requires-Python: >=3.10
License-File: LICENSE
Requires-Dist: torch>=2.0
Requires-Dist: torchvision>=0.17
Requires-Dist: tabulate>=0.9.0
Requires-Dist: networkx>=3.1
Requires-Dist: graphviz
Requires-Dist: matplotlib>=3.7.1
Requires-Dist: paramiko>=3.5.1
Dynamic: home-page
Dynamic: license-file
